Metadata-Version: 1.1
Name: digitseparator
Version: 0.0.2
Summary: separate digits
Home-page: UNKNOWN
Author: coldsober irene
Author-email: nseirene3@gmail.com
License: MIT
Keywords: spacing
Platform: UNKNOWN
Classifier: Development Status :: 5 - Production/Stable
Classifier: Intended Audience :: Education
Classifier: Operating System :: Microsoft :: Windows :: Windows 10
Classifier: License :: OSI Approved :: MIT License
Classifier: Programming Language :: Python :: 3
